thinagents/__init__.py
thinagents/core/__init__.py
thinagents/core/agent.py
thinagents/core/mcp.py
thinagents/core/response_models.py
thinagents/memory/__init__.py
thinagents/memory/base_memory.py
thinagents/memory/file_memory.py
thinagents/memory/in_memory.py
thinagents/memory/sqlite_memory.py
thinagents/tools/__init__.py
thinagents/tools/agno_tool.py
thinagents/tools/crewai_tool.py
thinagents/tools/langchain_tool.py
thinagents/tools/tool.py
thinagents/tools/toolkit.py
thinagents/utils/__init__.py
thinagents/utils/prompts.py
thinagents/utils/thread_pool_manager.py
thinagents/utils/visualize.py
thinagents/web/__init__.py
thinagents/web/backend/__init__.py
thinagents/web/backend/server.py
thinagents/web/backend/webui.py
thinagents/web/ui/build/chat.html
thinagents/web/ui/build/index.html
thinagents/web/ui/build/robots.txt
thinagents/web/ui/build/_app/env.js
thinagents/web/ui/build/_app/version.json
thinagents/web/ui/build/_app/immutable/assets/0.X95ks87V.css
thinagents/web/ui/build/_app/immutable/assets/3.BK-K8xVN.css
thinagents/web/ui/build/_app/immutable/assets/KaTeX_AMS-Regular.BQhdFMY1.woff2
thinagents/web/ui/build/_app/immutable/assets/KaTeX_AMS-Regular.DMm9YOAa.woff
thinagents/web/ui/build/_app/immutable/assets/KaTeX_AMS-Regular.DRggAlZN.ttf
thinagents/web/ui/build/_app/immutable/assets/KaTeX_Caligraphic-Bold.ATXxdsX0.ttf
thinagents/web/ui/build/_app/immutable/assets/KaTeX_Caligraphic-Bold.BEiXGLvX.woff
thinagents/web/ui/build/_app/immutable/assets/KaTeX_Caligraphic-Bold.Dq_IR9rO.woff2
thinagents/web/ui/build/_app/immutable/assets/KaTeX_Caligraphic-Regular.CTRA-rTL.woff
thinagents/web/ui/build/_app/immutable/assets/KaTeX_Caligraphic-Regular.Di6jR-x-.woff2
thinagents/web/ui/build/_app/immutable/assets/KaTeX_Caligraphic-Regular.wX97UBjC.ttf
thinagents/web/ui/build/_app/immutable/assets/KaTeX_Fraktur-Bold.BdnERNNW.ttf
thinagents/web/ui/build/_app/immutable/assets/KaTeX_Fraktur-Bold.BsDP51OF.woff
thinagents-0.0.19.dist-info/METADATA
thinagents-0.0.19.dist-info/WHEEL
thinagents-0.0.19.dist-info/top_level.txt
thinagents-0.0.19.dist-info/RECORD
