Metadata-Version: 2.4
Name: thinagents
Version: 0.0.19
Summary: A lightweight AI Agent framework
Home-page: https://github.com/PrabhuKiran8790/thinagents
Author: Prabhu Kiran Konda
License: MIT
Project-URL: Homepage, https://github.com/PrabhuKiran8790/thinagents
Keywords: AI,LLM,Agentic AI,AI Agents
Classifier: Programming Language :: Python :: 3
Classifier: License :: OSI Approved :: MIT License
Classifier: Operating System :: OS Independent
Requires-Python: >=3.10
Requires-Dist: litellm>=1.70.0
Requires-Dist: graphviz>=0.20.0
Provides-Extra: web
Requires-Dist: fastapi>=0.104.0; extra == "web"
Requires-Dist: uvicorn>=0.24.0; extra == "web"
Dynamic: home-page
Dynamic: requires-python
